ebo_api_bindings/__init__.py
ebo_api_bindings/api.py
ebo_api_bindings/base.py
ebo_api_bindings/calls.py
ebo_api_bindings/client.py
ebo_api_bindings/models.py
ebo_api_bindings-0.1.1.dist-info/METADATA
ebo_api_bindings-0.1.1.dist-info/WHEEL
ebo_api_bindings-0.1.1.dist-info/RECORD
