Metadata-Version: 2.3
Name: ebo-api-bindings
Version: 0.1.1
Summary: Simple KW bindings
Requires-Python: >=3.10
Requires-Dist: requests>=2.32.3
Requires-Dist: tqdm>=4.67.1
